{
  "nodes": [
    {
      "id": 119980,
      "x": 1029,
      "y": 424,
      "color": "b",
      "text": "Dog dirt on the pavement requires my complete, ground-focused attention on my way to work.",
      "text_begin": [],
      "text_end": [],
      "text_length": [
        90
      ],
      "comment": "",
      "type": "I",
      "scheme": "0",
      "descriptors": {},
      "cqdesc": {},
      "visible": true,
      "imgurl": "",
      "annotator": "",
      "date": "06/03/2019 - 14:31:23",
      "participantID": "0",
      "w": 200,
      "h": 70,
      "majorClaim": false
    },
    {
      "id": 119981,
      "x": 1016,
      "y": 240,
      "color": "b",
      "text": "This results in a lack of alertness in the road traffic comparable to a minor offense of the traffic regulations.",
      "text_begin": [],
      "text_end": [],
      "text_length": [
        113
      ],
      "comment": "",
      "type": "I",
      "scheme": "0",
      "descriptors": {},
      "cqdesc": {},
      "visible": true,
      "imgurl": "",
      "annotator": "",
      "date": "06/03/2019 - 14:31:23",
      "participantID": "0",
      "w": 200,
      "h": 90,
      "majorClaim": false
    },
    {
      "id": 119982,
      "x": 855,
      "y": 91,
      "color": "m",
      "text": "That's why causing such obstacles must to be more urgently punished.",
      "text_begin": [],
      "text_end": [],
      "text_length": [
        68
      ],
      "comment": "",
      "type": "I",
      "scheme": "0",
      "descriptors": {},
      "cqdesc": {},
      "visible": true,
      "imgurl": "",
      "annotator": "Anna Ludwig",
      "date": "23/03/2019 - 15:06:14",
      "participantID": "0",
      "w": 200,
      "h": 50,
      "majorClaim": true
    },
    {
      "id": 119983,
      "x": 722,
      "y": 241,
      "color": "b",
      "text": "Dog owners may think that dog dirt is only a harmless secretion of an animal like any other.",
      "text_begin": [],
      "text_end": [],
      "text_length": [
        92
      ],
      "comment": "",
      "type": "I",
      "scheme": "0",
      "descriptors": {},
      "cqdesc": {},
      "visible": true,
      "imgurl": "",
      "annotator": "",
      "date": "06/03/2019 - 14:31:23",
      "participantID": "0",
      "w": 200,
      "h": 70,
      "majorClaim": false
    },
    {
      "id": 119984,
      "x": 734,
      "y": 431,
      "color": "b",
      "text": "Yet then they misjudge its impact on road traffic.",
      "text_begin": [],
      "text_end": [],
      "text_length": [
        50
      ],
      "comment": "",
      "type": "I",
      "scheme": "0",
      "descriptors": {},
      "cqdesc": {},
      "visible": true,
      "imgurl": "",
      "annotator": "",
      "date": "06/03/2019 - 14:31:23",
      "participantID": "0",
      "w": 200,
      "h": 50,
      "majorClaim": false
    },
    {
      "id": 119985,
      "x": 1065,
      "y": 363,
      "color": "g",
      "text": "Sign",
      "text_begin": [],
      "text_end": [],
      "text_length": [],
      "comment": "",
      "type": "RA",
      "scheme": "30",
      "descriptors": {
        "s_General Premise։ B is generally indicated as true when its sign, A, is true": 119980,
        "s_Specific Premise։ A a finding A is true in this situation": null,
        "s_Conclusion։ B is true in this situation": 119981,
        "s_Expert Opinion։ Expert E asserts that proposition A is true/false": null
      },
      "cqdesc": {},
      "visible": true,
      "imgurl": "",
      "annotator": "Anna Ludwig",
      "date": "23/03/2019 - 15:08:16",
      "participantID": "0",
      "w": 52,
      "h": 30,
      "majorClaim": false
    },
    {
      "id": 119986,
      "x": 1062,
      "y": 172,
      "color": "g",
      "text": "Negative Consequences",
      "text_begin": [],
      "text_end": [],
      "text_length": [],
      "comment": "",
      "type": "RA",
      "scheme": "22",
      "descriptors": {
        "s_Premise։ If A is brought about, then bad consequences will occur": 119981,
        "s_Conclusion։ Therefore, A should not be brought about": 119982,
        "s_Expert Opinion։ Expert E asserts that proposition A is true/false": null
      },
      "cqdesc": {},
      "visible": true,
      "imgurl": "",
      "annotator": "Anna Ludwig",
      "date": "23/03/2019 - 15:07:33",
      "participantID": "0",
      "w": 143,
      "h": 30,
      "majorClaim": false
    },
    {
      "id": 119987,
      "x": 756,
      "y": 173,
      "color": "r",
      "text": "Default Conflict",
      "text_begin": [],
      "text_end": [],
      "text_length": [],
      "comment": "",
      "type": "CA",
      "scheme": "71",
      "descriptors": {},
      "cqdesc": {},
      "visible": true,
      "imgurl": "",
      "annotator": "Anna Ludwig",
      "date": "23/03/2019 - 15:06:17",
      "participantID": "0",
      "w": 103,
      "h": 30,
      "majorClaim": false
    },
    {
      "id": 119988,
      "x": 774,
      "y": 354,
      "color": "r",
      "text": "Default Conflict",
      "text_begin": [],
      "text_end": [],
      "text_length": [],
      "comment": "",
      "type": "CA",
      "scheme": "71",
      "descriptors": {},
      "cqdesc": {},
      "visible": true,
      "imgurl": "",
      "annotator": "Anna Ludwig",
      "date": "23/03/2019 - 15:06:21",
      "participantID": "0",
      "w": 103,
      "h": 30,
      "majorClaim": false
    }
  ],
  "edges": [
    {
      "from": {
        "id": 119980,
        "x": 1029,
        "y": 424,
        "color": "b",
        "text": "Dog dirt on the pavement requires my complete, ground-focused attention on my way to work.",
        "text_begin": [],
        "text_end": [],
        "text_length": [
          90
        ],
        "comment": "",
        "type": "I",
        "scheme": "0",
        "descriptors": {},
        "cqdesc": {},
        "visible": true,
        "imgurl": "",
        "annotator": "",
        "date": "06/03/2019 - 14:31:23",
        "participantID": "0",
        "w": 200,
        "h": 70,
        "majorClaim": false
      },
      "to": {
        "id": 119985,
        "x": 1065,
        "y": 363,
        "color": "g",
        "text": "Sign",
        "text_begin": [],
        "text_end": [],
        "text_length": [],
        "comment": "",
        "type": "RA",
        "scheme": "30",
        "descriptors": {
          "s_General Premise։ B is generally indicated as true when its sign, A, is true": 119980,
          "s_Specific Premise։ A a finding A is true in this situation": null,
          "s_Conclusion։ B is true in this situation": 119981,
          "s_Expert Opinion։ Expert E asserts that proposition A is true/false": null
        },
        "cqdesc": {},
        "visible": true,
        "imgurl": "",
        "annotator": "Anna Ludwig",
        "date": "23/03/2019 - 15:08:16",
        "participantID": "0",
        "w": 52,
        "h": 30,
        "majorClaim": false
      },
      "visible": true,
      "annotator": "",
      "date": "06/03/2019 - 14:31:23"
    },
    {
      "from": {
        "id": 119985,
        "x": 1065,
        "y": 363,
        "color": "g",
        "text": "Sign",
        "text_begin": [],
        "text_end": [],
        "text_length": [],
        "comment": "",
        "type": "RA",
        "scheme": "30",
        "descriptors": {
          "s_General Premise։ B is generally indicated as true when its sign, A, is true": 119980,
          "s_Specific Premise։ A a finding A is true in this situation": null,
          "s_Conclusion։ B is true in this situation": 119981,
          "s_Expert Opinion։ Expert E asserts that proposition A is true/false": null
        },
        "cqdesc": {},
        "visible": true,
        "imgurl": "",
        "annotator": "Anna Ludwig",
        "date": "23/03/2019 - 15:08:16",
        "participantID": "0",
        "w": 52,
        "h": 30,
        "majorClaim": false
      },
      "to": {
        "id": 119981,
        "x": 1016,
        "y": 240,
        "color": "b",
        "text": "This results in a lack of alertness in the road traffic comparable to a minor offense of the traffic regulations.",
        "text_begin": [],
        "text_end": [],
        "text_length": [
          113
        ],
        "comment": "",
        "type": "I",
        "scheme": "0",
        "descriptors": {},
        "cqdesc": {},
        "visible": true,
        "imgurl": "",
        "annotator": "",
        "date": "06/03/2019 - 14:31:23",
        "participantID": "0",
        "w": 200,
        "h": 90,
        "majorClaim": false
      },
      "visible": true,
      "annotator": "",
      "date": "06/03/2019 - 14:31:23"
    },
    {
      "from": {
        "id": 119981,
        "x": 1016,
        "y": 240,
        "color": "b",
        "text": "This results in a lack of alertness in the road traffic comparable to a minor offense of the traffic regulations.",
        "text_begin": [],
        "text_end": [],
        "text_length": [
          113
        ],
        "comment": "",
        "type": "I",
        "scheme": "0",
        "descriptors": {},
        "cqdesc": {},
        "visible": true,
        "imgurl": "",
        "annotator": "",
        "date": "06/03/2019 - 14:31:23",
        "participantID": "0",
        "w": 200,
        "h": 90,
        "majorClaim": false
      },
      "to": {
        "id": 119986,
        "x": 1062,
        "y": 172,
        "color": "g",
        "text": "Negative Consequences",
        "text_begin": [],
        "text_end": [],
        "text_length": [],
        "comment": "",
        "type": "RA",
        "scheme": "22",
        "descriptors": {
          "s_Premise։ If A is brought about, then bad consequences will occur": 119981,
          "s_Conclusion։ Therefore, A should not be brought about": 119982,
          "s_Expert Opinion։ Expert E asserts that proposition A is true/false": null
        },
        "cqdesc": {},
        "visible": true,
        "imgurl": "",
        "annotator": "Anna Ludwig",
        "date": "23/03/2019 - 15:07:33",
        "participantID": "0",
        "w": 143,
        "h": 30,
        "majorClaim": false
      },
      "visible": true,
      "annotator": "",
      "date": "06/03/2019 - 14:31:23"
    },
    {
      "from": {
        "id": 119986,
        "x": 1062,
        "y": 172,
        "color": "g",
        "text": "Negative Consequences",
        "text_begin": [],
        "text_end": [],
        "text_length": [],
        "comment": "",
        "type": "RA",
        "scheme": "22",
        "descriptors": {
          "s_Premise։ If A is brought about, then bad consequences will occur": 119981,
          "s_Conclusion։ Therefore, A should not be brought about": 119982,
          "s_Expert Opinion։ Expert E asserts that proposition A is true/false": null
        },
        "cqdesc": {},
        "visible": true,
        "imgurl": "",
        "annotator": "Anna Ludwig",
        "date": "23/03/2019 - 15:07:33",
        "participantID": "0",
        "w": 143,
        "h": 30,
        "majorClaim": false
      },
      "to": {
        "id": 119982,
        "x": 855,
        "y": 91,
        "color": "m",
        "text": "That's why causing such obstacles must to be more urgently punished.",
        "text_begin": [],
        "text_end": [],
        "text_length": [
          68
        ],
        "comment": "",
        "type": "I",
        "scheme": "0",
        "descriptors": {},
        "cqdesc": {},
        "visible": true,
        "imgurl": "",
        "annotator": "Anna Ludwig",
        "date": "23/03/2019 - 15:06:14",
        "participantID": "0",
        "w": 200,
        "h": 50,
        "majorClaim": true
      },
      "visible": true,
      "annotator": "",
      "date": "06/03/2019 - 14:31:23"
    },
    {
      "from": {
        "id": 119983,
        "x": 722,
        "y": 241,
        "color": "b",
        "text": "Dog owners may think that dog dirt is only a harmless secretion of an animal like any other.",
        "text_begin": [],
        "text_end": [],
        "text_length": [
          92
        ],
        "comment": "",
        "type": "I",
        "scheme": "0",
        "descriptors": {},
        "cqdesc": {},
        "visible": true,
        "imgurl": "",
        "annotator": "",
        "date": "06/03/2019 - 14:31:23",
        "participantID": "0",
        "w": 200,
        "h": 70,
        "majorClaim": false
      },
      "to": {
        "id": 119987,
        "x": 756,
        "y": 173,
        "color": "r",
        "text": "Default Conflict",
        "text_begin": [],
        "text_end": [],
        "text_length": [],
        "comment": "",
        "type": "CA",
        "scheme": "71",
        "descriptors": {},
        "cqdesc": {},
        "visible": true,
        "imgurl": "",
        "annotator": "Anna Ludwig",
        "date": "23/03/2019 - 15:06:17",
        "participantID": "0",
        "w": 103,
        "h": 30,
        "majorClaim": false
      },
      "visible": true,
      "annotator": "",
      "date": "06/03/2019 - 14:31:23"
    },
    {
      "from": {
        "id": 119987,
        "x": 756,
        "y": 173,
        "color": "r",
        "text": "Default Conflict",
        "text_begin": [],
        "text_end": [],
        "text_length": [],
        "comment": "",
        "type": "CA",
        "scheme": "71",
        "descriptors": {},
        "cqdesc": {},
        "visible": true,
        "imgurl": "",
        "annotator": "Anna Ludwig",
        "date": "23/03/2019 - 15:06:17",
        "participantID": "0",
        "w": 103,
        "h": 30,
        "majorClaim": false
      },
      "to": {
        "id": 119982,
        "x": 855,
        "y": 91,
        "color": "m",
        "text": "That's why causing such obstacles must to be more urgently punished.",
        "text_begin": [],
        "text_end": [],
        "text_length": [
          68
        ],
        "comment": "",
        "type": "I",
        "scheme": "0",
        "descriptors": {},
        "cqdesc": {},
        "visible": true,
        "imgurl": "",
        "annotator": "Anna Ludwig",
        "date": "23/03/2019 - 15:06:14",
        "participantID": "0",
        "w": 200,
        "h": 50,
        "majorClaim": true
      },
      "visible": true,
      "annotator": "",
      "date": "06/03/2019 - 14:31:23"
    },
    {
      "from": {
        "id": 119984,
        "x": 734,
        "y": 431,
        "color": "b",
        "text": "Yet then they misjudge its impact on road traffic.",
        "text_begin": [],
        "text_end": [],
        "text_length": [
          50
        ],
        "comment": "",
        "type": "I",
        "scheme": "0",
        "descriptors": {},
        "cqdesc": {},
        "visible": true,
        "imgurl": "",
        "annotator": "",
        "date": "06/03/2019 - 14:31:23",
        "participantID": "0",
        "w": 200,
        "h": 50,
        "majorClaim": false
      },
      "to": {
        "id": 119988,
        "x": 774,
        "y": 354,
        "color": "r",
        "text": "Default Conflict",
        "text_begin": [],
        "text_end": [],
        "text_length": [],
        "comment": "",
        "type": "CA",
        "scheme": "71",
        "descriptors": {},
        "cqdesc": {},
        "visible": true,
        "imgurl": "",
        "annotator": "Anna Ludwig",
        "date": "23/03/2019 - 15:06:21",
        "participantID": "0",
        "w": 103,
        "h": 30,
        "majorClaim": false
      },
      "visible": true,
      "annotator": "",
      "date": "06/03/2019 - 14:31:23"
    },
    {
      "from": {
        "id": 119988,
        "x": 774,
        "y": 354,
        "color": "r",
        "text": "Default Conflict",
        "text_begin": [],
        "text_end": [],
        "text_length": [],
        "comment": "",
        "type": "CA",
        "scheme": "71",
        "descriptors": {},
        "cqdesc": {},
        "visible": true,
        "imgurl": "",
        "annotator": "Anna Ludwig",
        "date": "23/03/2019 - 15:06:21",
        "participantID": "0",
        "w": 103,
        "h": 30,
        "majorClaim": false
      },
      "to": {
        "id": 119983,
        "x": 722,
        "y": 241,
        "color": "b",
        "text": "Dog owners may think that dog dirt is only a harmless secretion of an animal like any other.",
        "text_begin": [],
        "text_end": [],
        "text_length": [
          92
        ],
        "comment": "",
        "type": "I",
        "scheme": "0",
        "descriptors": {},
        "cqdesc": {},
        "visible": true,
        "imgurl": "",
        "annotator": "",
        "date": "06/03/2019 - 14:31:23",
        "participantID": "0",
        "w": 200,
        "h": 70,
        "majorClaim": false
      },
      "visible": true,
      "annotator": "",
      "date": "06/03/2019 - 14:31:23"
    }
  ],
  "participants": [],
  "analysis": {
    "txt": "<span class=\"highlighted\" id=\"node119980\">Dog dirt on the pavement requires my complete, ground-focused attention on my way to work.</span> <span class=\"highlighted\" id=\"node119981\">This results in a lack of alertness in the road traffic comparable to a minor offense of the traffic regulations.</span> <span class=\"highlighted\" id=\"node119982\">That's why causing such obstacles must to be more urgently punished.</span> <span class=\"highlighted\" id=\"node119983\">Dog owners may think that dog dirt is only a harmless secretion of an animal like any other.</span> <span class=\"highlighted\" id=\"node119984\">Yet then they misjudge its impact on road traffic.</span><br>",
    "plain_txt": "Dog dirt on the pavement requires my complete, ground-focused attention on my way to work. This results in a lack of alertness in the road traffic comparable to a minor offense of the traffic regulations. That's why causing such obstacles must to be more urgently punished. Dog owners may think that dog dirt is only a harmless secretion of an animal like any other. Yet then they misjudge its impact on road traffic.\n",
    "annotatorName": "Anna Ludwig",
    "documentTitle": "nodeset6367.json"
  }
}