{
  "nodes": [
    {
      "id": 120741,
      "x": 987,
      "y": 77,
      "color": "m",
      "text": "Germany should by no means introduce capital punishment.",
      "text_begin": [],
      "text_end": [],
      "text_length": [
        56
      ],
      "comment": "",
      "type": "I",
      "scheme": "0",
      "descriptors": {},
      "cqdesc": {},
      "visible": true,
      "imgurl": "",
      "annotator": "Anna Ludwig",
      "date": "12/03/2019 - 16:08:38",
      "participantID": "0",
      "w": 200,
      "h": 50,
      "majorClaim": true
    },
    {
      "id": 120742,
      "x": 1199,
      "y": 279,
      "color": "b",
      "text": "If there were capital punishment, this would mean people are allowed to put themselves above others and rule over their lives.",
      "text_begin": [],
      "text_end": [],
      "text_length": [
        126
      ],
      "comment": "",
      "type": "I",
      "scheme": "0",
      "descriptors": {},
      "cqdesc": {},
      "visible": true,
      "imgurl": "",
      "annotator": "",
      "date": "06/03/2019 - 14:31:23",
      "participantID": "0",
      "w": 200,
      "h": 90,
      "majorClaim": false
    },
    {
      "id": 120743,
      "x": 984,
      "y": 277,
      "color": "b",
      "text": "Capital punishment would be murder and would have to be punished with the death penalty itself.",
      "text_begin": [],
      "text_end": [],
      "text_length": [
        95
      ],
      "comment": "",
      "type": "I",
      "scheme": "0",
      "descriptors": {},
      "cqdesc": {},
      "visible": true,
      "imgurl": "",
      "annotator": "",
      "date": "06/03/2019 - 14:31:23",
      "participantID": "0",
      "w": 200,
      "h": 90,
      "majorClaim": false
    },
    {
      "id": 120744,
      "x": 772,
      "y": 271,
      "color": "b",
      "text": "What, then, ought to be done with criminals who have committed truly awful crimes such as murder or rape - should they simply be allowed to live on",
      "text_begin": [],
      "text_end": [],
      "text_length": [
        147
      ],
      "comment": "",
      "type": "I",
      "scheme": "0",
      "descriptors": {},
      "cqdesc": {},
      "visible": true,
      "imgurl": "",
      "annotator": "",
      "date": "06/03/2019 - 14:31:23",
      "participantID": "0",
      "w": 200,
      "h": 110,
      "majorClaim": false
    },
    {
      "id": 120745,
      "x": 776,
      "y": 493,
      "color": "b",
      "text": "although they have taken or destroyed another life?",
      "text_begin": [],
      "text_end": [],
      "text_length": [
        51
      ],
      "comment": "",
      "type": "I",
      "scheme": "0",
      "descriptors": {},
      "cqdesc": {},
      "visible": true,
      "imgurl": "",
      "annotator": "",
      "date": "06/03/2019 - 14:31:23",
      "participantID": "0",
      "w": 200,
      "h": 50,
      "majorClaim": false
    },
    {
      "id": 120746,
      "x": 399,
      "y": 395,
      "color": "b",
      "text": "Yes, for it is a much graver punishment to be imprisoned forever and be tortured by one's own thoughts than to be killed quickly and easily by an injection.",
      "text_begin": [],
      "text_end": [],
      "text_length": [
        156
      ],
      "comment": "",
      "type": "I",
      "scheme": "0",
      "descriptors": {},
      "cqdesc": {},
      "visible": true,
      "imgurl": "",
      "annotator": "",
      "date": "06/03/2019 - 14:31:23",
      "participantID": "0",
      "w": 200,
      "h": 110,
      "majorClaim": false
    },
    {
      "id": 120747,
      "x": 1235,
      "y": 218,
      "color": "g",
      "text": "Negative Consequences",
      "text_begin": [],
      "text_end": [],
      "text_length": [],
      "comment": "",
      "type": "RA",
      "scheme": "22",
      "descriptors": {
        "s_Premise։ If A is brought about, then bad consequences will occur": 120742,
        "s_Conclusion։ Therefore, A should not be brought about": 120741,
        "s_Expert Opinion։ Expert E asserts that proposition A is true/false": null
      },
      "cqdesc": {},
      "visible": true,
      "imgurl": "",
      "annotator": "Anna Ludwig",
      "date": "12/03/2019 - 16:09:40",
      "participantID": "0",
      "w": 143,
      "h": 30,
      "majorClaim": false
    },
    {
      "id": 120748,
      "x": 1025,
      "y": 216,
      "color": "g",
      "text": "Negative Consequences",
      "text_begin": [],
      "text_end": [],
      "text_length": [],
      "comment": "",
      "type": "RA",
      "scheme": "22",
      "descriptors": {
        "s_Premise։ If A is brought about, then bad consequences will occur": 120743,
        "s_Conclusion։ Therefore, A should not be brought about": 120741,
        "s_Expert Opinion։ Expert E asserts that proposition A is true/false": null
      },
      "cqdesc": {},
      "visible": true,
      "imgurl": "",
      "annotator": "Anna Ludwig",
      "date": "12/03/2019 - 16:09:49",
      "participantID": "0",
      "w": 143,
      "h": 30,
      "majorClaim": false
    },
    {
      "id": 120749,
      "x": 811,
      "y": 213,
      "color": "g",
      "text": "Cause to Effect",
      "text_begin": [],
      "text_end": [],
      "text_length": [],
      "comment": "",
      "type": "RA",
      "scheme": "4",
      "descriptors": {
        "s_Major Premise։ Generally, if A occurs, then B will∕might occur": 120744,
        "s_Minor Premise։ In this case, A occurs∕might occur": null,
        "s_Conclusion։ Therefore, in this case, B will∕might occur": 120741,
        "s_Expert Opinion։ Expert E asserts that proposition A is true/false": null
      },
      "cqdesc": {},
      "visible": true,
      "imgurl": "",
      "annotator": "Anna Ludwig",
      "date": "12/03/2019 - 16:13:04",
      "participantID": "0",
      "w": 101,
      "h": 30,
      "majorClaim": false
    },
    {
      "id": 120750,
      "x": 824,
      "y": 427,
      "color": "r",
      "text": "Default Conflict",
      "text_begin": [],
      "text_end": [],
      "text_length": [],
      "comment": "",
      "type": "CA",
      "scheme": "71",
      "descriptors": {},
      "cqdesc": {},
      "visible": true,
      "imgurl": "",
      "annotator": "Anna Ludwig",
      "date": "12/03/2019 - 16:08:27",
      "participantID": "0",
      "w": 103,
      "h": 30,
      "majorClaim": false
    },
    {
      "id": 120751,
      "x": 647,
      "y": 426,
      "color": "r",
      "text": "Default Conflict",
      "text_begin": [],
      "text_end": [],
      "text_length": [],
      "comment": "",
      "type": "CA",
      "scheme": "71",
      "descriptors": {},
      "cqdesc": {},
      "visible": true,
      "imgurl": "",
      "annotator": "Anna Ludwig",
      "date": "12/03/2019 - 16:08:31",
      "participantID": "0",
      "w": 103,
      "h": 30,
      "majorClaim": false
    }
  ],
  "edges": [
    {
      "from": {
        "id": 120742,
        "x": 1199,
        "y": 279,
        "color": "b",
        "text": "If there were capital punishment, this would mean people are allowed to put themselves above others and rule over their lives.",
        "text_begin": [],
        "text_end": [],
        "text_length": [
          126
        ],
        "comment": "",
        "type": "I",
        "scheme": "0",
        "descriptors": {},
        "cqdesc": {},
        "visible": true,
        "imgurl": "",
        "annotator": "",
        "date": "06/03/2019 - 14:31:23",
        "participantID": "0",
        "w": 200,
        "h": 90,
        "majorClaim": false
      },
      "to": {
        "id": 120747,
        "x": 1235,
        "y": 218,
        "color": "g",
        "text": "Negative Consequences",
        "text_begin": [],
        "text_end": [],
        "text_length": [],
        "comment": "",
        "type": "RA",
        "scheme": "22",
        "descriptors": {
          "s_Premise։ If A is brought about, then bad consequences will occur": 120742,
          "s_Conclusion։ Therefore, A should not be brought about": 120741,
          "s_Expert Opinion։ Expert E asserts that proposition A is true/false": null
        },
        "cqdesc": {},
        "visible": true,
        "imgurl": "",
        "annotator": "Anna Ludwig",
        "date": "12/03/2019 - 16:09:40",
        "participantID": "0",
        "w": 143,
        "h": 30,
        "majorClaim": false
      },
      "visible": true,
      "annotator": "",
      "date": "06/03/2019 - 14:31:23"
    },
    {
      "from": {
        "id": 120747,
        "x": 1235,
        "y": 218,
        "color": "g",
        "text": "Negative Consequences",
        "text_begin": [],
        "text_end": [],
        "text_length": [],
        "comment": "",
        "type": "RA",
        "scheme": "22",
        "descriptors": {
          "s_Premise։ If A is brought about, then bad consequences will occur": 120742,
          "s_Conclusion։ Therefore, A should not be brought about": 120741,
          "s_Expert Opinion։ Expert E asserts that proposition A is true/false": null
        },
        "cqdesc": {},
        "visible": true,
        "imgurl": "",
        "annotator": "Anna Ludwig",
        "date": "12/03/2019 - 16:09:40",
        "participantID": "0",
        "w": 143,
        "h": 30,
        "majorClaim": false
      },
      "to": {
        "id": 120741,
        "x": 987,
        "y": 77,
        "color": "m",
        "text": "Germany should by no means introduce capital punishment.",
        "text_begin": [],
        "text_end": [],
        "text_length": [
          56
        ],
        "comment": "",
        "type": "I",
        "scheme": "0",
        "descriptors": {},
        "cqdesc": {},
        "visible": true,
        "imgurl": "",
        "annotator": "Anna Ludwig",
        "date": "12/03/2019 - 16:08:38",
        "participantID": "0",
        "w": 200,
        "h": 50,
        "majorClaim": true
      },
      "visible": true,
      "annotator": "",
      "date": "06/03/2019 - 14:31:23"
    },
    {
      "from": {
        "id": 120743,
        "x": 984,
        "y": 277,
        "color": "b",
        "text": "Capital punishment would be murder and would have to be punished with the death penalty itself.",
        "text_begin": [],
        "text_end": [],
        "text_length": [
          95
        ],
        "comment": "",
        "type": "I",
        "scheme": "0",
        "descriptors": {},
        "cqdesc": {},
        "visible": true,
        "imgurl": "",
        "annotator": "",
        "date": "06/03/2019 - 14:31:23",
        "participantID": "0",
        "w": 200,
        "h": 90,
        "majorClaim": false
      },
      "to": {
        "id": 120748,
        "x": 1025,
        "y": 216,
        "color": "g",
        "text": "Negative Consequences",
        "text_begin": [],
        "text_end": [],
        "text_length": [],
        "comment": "",
        "type": "RA",
        "scheme": "22",
        "descriptors": {
          "s_Premise։ If A is brought about, then bad consequences will occur": 120743,
          "s_Conclusion։ Therefore, A should not be brought about": 120741,
          "s_Expert Opinion։ Expert E asserts that proposition A is true/false": null
        },
        "cqdesc": {},
        "visible": true,
        "imgurl": "",
        "annotator": "Anna Ludwig",
        "date": "12/03/2019 - 16:09:49",
        "participantID": "0",
        "w": 143,
        "h": 30,
        "majorClaim": false
      },
      "visible": true,
      "annotator": "",
      "date": "06/03/2019 - 14:31:23"
    },
    {
      "from": {
        "id": 120748,
        "x": 1025,
        "y": 216,
        "color": "g",
        "text": "Negative Consequences",
        "text_begin": [],
        "text_end": [],
        "text_length": [],
        "comment": "",
        "type": "RA",
        "scheme": "22",
        "descriptors": {
          "s_Premise։ If A is brought about, then bad consequences will occur": 120743,
          "s_Conclusion։ Therefore, A should not be brought about": 120741,
          "s_Expert Opinion։ Expert E asserts that proposition A is true/false": null
        },
        "cqdesc": {},
        "visible": true,
        "imgurl": "",
        "annotator": "Anna Ludwig",
        "date": "12/03/2019 - 16:09:49",
        "participantID": "0",
        "w": 143,
        "h": 30,
        "majorClaim": false
      },
      "to": {
        "id": 120741,
        "x": 987,
        "y": 77,
        "color": "m",
        "text": "Germany should by no means introduce capital punishment.",
        "text_begin": [],
        "text_end": [],
        "text_length": [
          56
        ],
        "comment": "",
        "type": "I",
        "scheme": "0",
        "descriptors": {},
        "cqdesc": {},
        "visible": true,
        "imgurl": "",
        "annotator": "Anna Ludwig",
        "date": "12/03/2019 - 16:08:38",
        "participantID": "0",
        "w": 200,
        "h": 50,
        "majorClaim": true
      },
      "visible": true,
      "annotator": "",
      "date": "06/03/2019 - 14:31:23"
    },
    {
      "from": {
        "id": 120744,
        "x": 772,
        "y": 271,
        "color": "b",
        "text": "What, then, ought to be done with criminals who have committed truly awful crimes such as murder or rape - should they simply be allowed to live on",
        "text_begin": [],
        "text_end": [],
        "text_length": [
          147
        ],
        "comment": "",
        "type": "I",
        "scheme": "0",
        "descriptors": {},
        "cqdesc": {},
        "visible": true,
        "imgurl": "",
        "annotator": "",
        "date": "06/03/2019 - 14:31:23",
        "participantID": "0",
        "w": 200,
        "h": 110,
        "majorClaim": false
      },
      "to": {
        "id": 120749,
        "x": 811,
        "y": 213,
        "color": "g",
        "text": "Cause to Effect",
        "text_begin": [],
        "text_end": [],
        "text_length": [],
        "comment": "",
        "type": "RA",
        "scheme": "4",
        "descriptors": {
          "s_Major Premise։ Generally, if A occurs, then B will∕might occur": 120744,
          "s_Minor Premise։ In this case, A occurs∕might occur": null,
          "s_Conclusion։ Therefore, in this case, B will∕might occur": 120741,
          "s_Expert Opinion։ Expert E asserts that proposition A is true/false": null
        },
        "cqdesc": {},
        "visible": true,
        "imgurl": "",
        "annotator": "Anna Ludwig",
        "date": "12/03/2019 - 16:13:04",
        "participantID": "0",
        "w": 101,
        "h": 30,
        "majorClaim": false
      },
      "visible": true,
      "annotator": "",
      "date": "06/03/2019 - 14:31:23"
    },
    {
      "from": {
        "id": 120749,
        "x": 811,
        "y": 213,
        "color": "g",
        "text": "Cause to Effect",
        "text_begin": [],
        "text_end": [],
        "text_length": [],
        "comment": "",
        "type": "RA",
        "scheme": "4",
        "descriptors": {
          "s_Major Premise։ Generally, if A occurs, then B will∕might occur": 120744,
          "s_Minor Premise։ In this case, A occurs∕might occur": null,
          "s_Conclusion։ Therefore, in this case, B will∕might occur": 120741,
          "s_Expert Opinion։ Expert E asserts that proposition A is true/false": null
        },
        "cqdesc": {},
        "visible": true,
        "imgurl": "",
        "annotator": "Anna Ludwig",
        "date": "12/03/2019 - 16:13:04",
        "participantID": "0",
        "w": 101,
        "h": 30,
        "majorClaim": false
      },
      "to": {
        "id": 120741,
        "x": 987,
        "y": 77,
        "color": "m",
        "text": "Germany should by no means introduce capital punishment.",
        "text_begin": [],
        "text_end": [],
        "text_length": [
          56
        ],
        "comment": "",
        "type": "I",
        "scheme": "0",
        "descriptors": {},
        "cqdesc": {},
        "visible": true,
        "imgurl": "",
        "annotator": "Anna Ludwig",
        "date": "12/03/2019 - 16:08:38",
        "participantID": "0",
        "w": 200,
        "h": 50,
        "majorClaim": true
      },
      "visible": true,
      "annotator": "",
      "date": "06/03/2019 - 14:31:23"
    },
    {
      "from": {
        "id": 120745,
        "x": 776,
        "y": 493,
        "color": "b",
        "text": "although they have taken or destroyed another life?",
        "text_begin": [],
        "text_end": [],
        "text_length": [
          51
        ],
        "comment": "",
        "type": "I",
        "scheme": "0",
        "descriptors": {},
        "cqdesc": {},
        "visible": true,
        "imgurl": "",
        "annotator": "",
        "date": "06/03/2019 - 14:31:23",
        "participantID": "0",
        "w": 200,
        "h": 50,
        "majorClaim": false
      },
      "to": {
        "id": 120750,
        "x": 824,
        "y": 427,
        "color": "r",
        "text": "Default Conflict",
        "text_begin": [],
        "text_end": [],
        "text_length": [],
        "comment": "",
        "type": "CA",
        "scheme": "71",
        "descriptors": {},
        "cqdesc": {},
        "visible": true,
        "imgurl": "",
        "annotator": "Anna Ludwig",
        "date": "12/03/2019 - 16:08:27",
        "participantID": "0",
        "w": 103,
        "h": 30,
        "majorClaim": false
      },
      "visible": true,
      "annotator": "",
      "date": "06/03/2019 - 14:31:23"
    },
    {
      "from": {
        "id": 120750,
        "x": 824,
        "y": 427,
        "color": "r",
        "text": "Default Conflict",
        "text_begin": [],
        "text_end": [],
        "text_length": [],
        "comment": "",
        "type": "CA",
        "scheme": "71",
        "descriptors": {},
        "cqdesc": {},
        "visible": true,
        "imgurl": "",
        "annotator": "Anna Ludwig",
        "date": "12/03/2019 - 16:08:27",
        "participantID": "0",
        "w": 103,
        "h": 30,
        "majorClaim": false
      },
      "to": {
        "id": 120744,
        "x": 772,
        "y": 271,
        "color": "b",
        "text": "What, then, ought to be done with criminals who have committed truly awful crimes such as murder or rape - should they simply be allowed to live on",
        "text_begin": [],
        "text_end": [],
        "text_length": [
          147
        ],
        "comment": "",
        "type": "I",
        "scheme": "0",
        "descriptors": {},
        "cqdesc": {},
        "visible": true,
        "imgurl": "",
        "annotator": "",
        "date": "06/03/2019 - 14:31:23",
        "participantID": "0",
        "w": 200,
        "h": 110,
        "majorClaim": false
      },
      "visible": true,
      "annotator": "",
      "date": "06/03/2019 - 14:31:23"
    },
    {
      "from": {
        "id": 120746,
        "x": 399,
        "y": 395,
        "color": "b",
        "text": "Yes, for it is a much graver punishment to be imprisoned forever and be tortured by one's own thoughts than to be killed quickly and easily by an injection.",
        "text_begin": [],
        "text_end": [],
        "text_length": [
          156
        ],
        "comment": "",
        "type": "I",
        "scheme": "0",
        "descriptors": {},
        "cqdesc": {},
        "visible": true,
        "imgurl": "",
        "annotator": "",
        "date": "06/03/2019 - 14:31:23",
        "participantID": "0",
        "w": 200,
        "h": 110,
        "majorClaim": false
      },
      "to": {
        "id": 120751,
        "x": 647,
        "y": 426,
        "color": "r",
        "text": "Default Conflict",
        "text_begin": [],
        "text_end": [],
        "text_length": [],
        "comment": "",
        "type": "CA",
        "scheme": "71",
        "descriptors": {},
        "cqdesc": {},
        "visible": true,
        "imgurl": "",
        "annotator": "Anna Ludwig",
        "date": "12/03/2019 - 16:08:31",
        "participantID": "0",
        "w": 103,
        "h": 30,
        "majorClaim": false
      },
      "visible": true,
      "annotator": "",
      "date": "06/03/2019 - 14:31:23"
    },
    {
      "from": {
        "id": 120751,
        "x": 647,
        "y": 426,
        "color": "r",
        "text": "Default Conflict",
        "text_begin": [],
        "text_end": [],
        "text_length": [],
        "comment": "",
        "type": "CA",
        "scheme": "71",
        "descriptors": {},
        "cqdesc": {},
        "visible": true,
        "imgurl": "",
        "annotator": "Anna Ludwig",
        "date": "12/03/2019 - 16:08:31",
        "participantID": "0",
        "w": 103,
        "h": 30,
        "majorClaim": false
      },
      "to": {
        "id": 120750,
        "x": 824,
        "y": 427,
        "color": "r",
        "text": "Default Conflict",
        "text_begin": [],
        "text_end": [],
        "text_length": [],
        "comment": "",
        "type": "CA",
        "scheme": "71",
        "descriptors": {},
        "cqdesc": {},
        "visible": true,
        "imgurl": "",
        "annotator": "Anna Ludwig",
        "date": "12/03/2019 - 16:08:27",
        "participantID": "0",
        "w": 103,
        "h": 30,
        "majorClaim": false
      },
      "visible": true,
      "annotator": "",
      "date": "06/03/2019 - 14:31:23"
    }
  ],
  "participants": [],
  "analysis": {
    "txt": "<span class=\"highlighted\" id=\"node120741\">Germany should by no means introduce capital punishment.</span> <span class=\"highlighted\" id=\"node120742\">If there were capital punishment, this would mean people are allowed to put themselves above others and rule over their lives.</span> <span class=\"highlighted\" id=\"node120743\">Capital punishment would be murder and would have to be punished with the death penalty itself.</span> <span class=\"highlighted\" id=\"node120744\">What, then, ought to be done with criminals who have committed truly awful crimes such as murder or rape - should they simply be allowed to live on</span> <span class=\"highlighted\" id=\"node120745\">although they have taken or destroyed another life?</span> <span class=\"highlighted\" id=\"node120746\">Yes, for it is a much graver punishment to be imprisoned forever and be tortured by one's own thoughts than to be killed quickly and easily by an injection.</span><br>",
    "plain_txt": "Germany should by no means introduce capital punishment. If there were capital punishment, this would mean people are allowed to put themselves above others and rule over their lives. Capital punishment would be murder and would have to be punished with the death penalty itself. What, then, ought to be done with criminals who have committed truly awful crimes such as murder or rape - should they simply be allowed to live on although they have taken or destroyed another life? Yes, for it is a much graver punishment to be imprisoned forever and be tortured by one's own thoughts than to be killed quickly and easily by an injection.\n",
    "annotatorName": "Anna Ludwig",
    "documentTitle": "nodeset6453.json"
  }
}